jsonscribe/__init__.py
jsonscribe/filters.py
jsonscribe/formatters.py
jsonscribe/utils.py
json_scribe-2.0.0.dist-info/METADATA
json_scribe-2.0.0.dist-info/WHEEL
json_scribe-2.0.0.dist-info/top_level.txt
json_scribe-2.0.0.dist-info/RECORD
