Metadata-Version: 2.1
Name: json-scribe
Version: 2.0.0
Summary: JSON-based logging for the masses
Home-page: https://github.com/aweber/json-scribe
Author: AWeber Communications, Inc
Author-email: api@aweber.com
License: UNKNOWN
Platform: UNKNOWN
Classifier: Development Status :: 5 - Production/Stable
Classifier: Intended Audience :: Developers
Classifier: License :: OSI Approved :: BSD License
Classifier: Natural Language :: English
Classifier: Operating System :: OS Independent
Classifier: Programming Language :: Python :: 2
Classifier: Programming Language :: Python :: 2.6
Classifier: Programming Language :: Python :: 3
Classifier: Programming Language :: Python :: 3.7
Classifier: Programming Language :: Python :: 3.8
Classifier: Programming Language :: Python :: 3.9
Provides-Extra: dev
Requires-Dist: coverage (==5.5) ; extra == 'dev'
Requires-Dist: flake8 (==3.9.2) ; extra == 'dev'
Requires-Dist: readme-renderer (==21.0) ; extra == 'dev'
Requires-Dist: wheel (==0.36.2) ; extra == 'dev'
Requires-Dist: yapf (==0.22.0) ; extra == 'dev'
Requires-Dist: Sphinx (==1.8.5) ; (python_version < "3") and extra == 'dev'
Requires-Dist: Sphinx (==4.0.1) ; (python_version >= "3.7") and extra == 'dev'
Provides-Extra: readthedocs
Requires-Dist: Sphinx (==4.0.1) ; extra == 'readthedocs'
